albion_similog/__init__.py
albion_similog/log.py
albion_similog/prepare_data.py
albion_similog/run_example.py
albion_similog/well_correlation.py
albion_similog-0.3.7.dist-info/METADATA
albion_similog-0.3.7.dist-info/WHEEL
albion_similog-0.3.7.dist-info/top_level.txt
albion_similog-0.3.7.dist-info/RECORD
