Metadata-Version: 2.1
Name: albion-similog
Version: 0.3.7
Summary: Compute a consensus dataseries with FAMSA algorithm.
Home-page: 
Author: Oslandia
Author-email: infos@oslandia.com
Maintainer: Oslandia
Maintainer-email: infos@oslandia.com
Classifier: Development Status :: 4 - Beta
Classifier: Intended Audience :: Developers
Classifier: Operating System :: OS Independent
Classifier: Programming Language :: Python :: 3.7
Classifier: Programming Language :: Python :: 3.8
Classifier: Programming Language :: Python :: 3.9
Classifier: Programming Language :: Python :: 3.10
Classifier: Programming Language :: Python :: Implementation :: CPython
